adafruit_neopxl8.py
adafruit_circuitpython_neopxl8-0.3.6.dist-info/licenses/LICENSE
adafruit_circuitpython_neopxl8-0.3.6.dist-info/METADATA
adafruit_circuitpython_neopxl8-0.3.6.dist-info/WHEEL
adafruit_circuitpython_neopxl8-0.3.6.dist-info/top_level.txt
adafruit_circuitpython_neopxl8-0.3.6.dist-info/RECORD
