Metadata-Version: 2.4
Name: adafruit-circuitpython-neopxl8
Version: 0.3.6
Summary: PIO-driven 8-way concurrent NeoPixel driver for RP2040
Author-email: Adafruit Industries <circuitpython@adafruit.com>
License: MIT
Project-URL: Homepage, https://github.com/adafruit/Adafruit_CircuitPython_neopxl8
Keywords: adafruit,blinka,circuitpython,micropython,neopxl8,neopixel,rp2040,rgb,rgbw,led,animation
Classifier: Intended Audience :: Developers
Classifier: Topic :: Software Development :: Libraries
Classifier: Topic :: Software Development :: Embedded Systems
Classifier: Topic :: System :: Hardware
Classifier: License :: OSI Approved :: MIT License
Classifier: Programming Language :: Python :: 3
License-File: LICENSE
Requires-Dist: Adafruit-Blinka
Requires-Dist: Adafruit-CircuitPython-pioasm
Requires-Dist: Adafruit-CircuitPython-PixelBuf
Provides-Extra: optional
Dynamic: license-file
